Metadata-Version: 2.1
Name: cython-setuptools
Version: 0.2.2
Summary: Cython setuptools integration
Home-page: https://github.com/flupke/cython-setuptools
Author: Luper Rouch
Author-email: luper.rouch@gmail.com
License: UNKNOWN
Keywords: cython setuptools
Platform: UNKNOWN
Classifier: Framework :: Setuptools Plugin
Classifier: Topic :: Software Development :: Build Tools
Classifier: License :: OSI Approved :: MIT License
Provides-Extra: dev
